fosforio/__init__.py
fosforio/amazons3.py
fosforio/azure.py
fosforio/feature_store.py
fosforio/fosforio.py
fosforio/hive.py
fosforio/manager.py
fosforio/mysql.py
fosforio/postgres.py
fosforio/sftp.py
fosforio/snowflake.py
fosforio/sqlserver.py
fosforio-1.0.3.dist-info/METADATA
fosforio-1.0.3.dist-info/WHEEL
fosforio-1.0.3.dist-info/top_level.txt
fosforio-1.0.3.dist-info/RECORD
