Metadata-Version: 2.1
Name: fosforio
Version: 1.0.3
Summary: FOSFOR-IO: To read and write dataframe from different connectors.
Home-page: UNKNOWN
Author: Abhishek Chaurasia
Author-email: <abhishek1.chaurasia@fosfor.com>
License: UNKNOWN
Project-URL: Product, https://www.fosfor.com/
Project-URL: Source, https://gitlab.fosfor.com/fosfor-decision-cloud/intelligence/refract-sdk
Keywords: fosforio
Platform: UNKNOWN
Classifier: Programming Language :: Python :: 3.8
Requires-Dist: pandas ==2.0.0
Provides-Extra: all
Requires-Dist: snowflake-connector-python[pandas] ==3.6.0 ; extra == 'all'
Requires-Dist: boto3 ==1.26.116 ; extra == 'all'
Requires-Dist: azure ==4.0.0 ; extra == 'all'
Requires-Dist: openpyxl ==3.1.2 ; extra == 'all'
Requires-Dist: xlrd ==2.0.1 ; extra == 'all'
Requires-Dist: pysftp ==0.2.9 ; extra == 'all'
Requires-Dist: pymysql ==1.0.3 ; extra == 'all'
Requires-Dist: impyla ==0.16.2 ; extra == 'all'
Requires-Dist: thrift-sasl ==0.4.3 ; extra == 'all'
Requires-Dist: pure-sasl ==0.6.2 ; extra == 'all'
Requires-Dist: PyHive ==0.6.3.dev0 ; extra == 'all'
Requires-Dist: pyodbc ==4.0.39 ; extra == 'all'
Requires-Dist: psycopg2-binary ==2.9.6 ; extra == 'all'
Provides-Extra: azureblob
Requires-Dist: azure ==4.0.0 ; extra == 'azureblob'
Provides-Extra: hive
Requires-Dist: impyla ==0.16.2 ; extra == 'hive'
Requires-Dist: thrift-sasl ==0.4.3 ; extra == 'hive'
Requires-Dist: pure-sasl ==0.6.2 ; extra == 'hive'
Requires-Dist: PyHive ==0.6.3.dev0 ; extra == 'hive'
Requires-Dist: refractpyhive ==0.0.3.dev0 ; extra == 'hive'
Provides-Extra: local
Requires-Dist: openpyxl ==3.1.2 ; extra == 'local'
Requires-Dist: xlrd ==2.0.1 ; extra == 'local'
Provides-Extra: mysql
Requires-Dist: pymysql ==1.0.3 ; extra == 'mysql'
Provides-Extra: postgres
Requires-Dist: psycopg2-binary ==2.9.6 ; extra == 'postgres'
Provides-Extra: s3
Requires-Dist: boto3 ==1.26.116 ; extra == 's3'
Provides-Extra: sftp
Requires-Dist: pysftp ==0.2.9 ; extra == 'sftp'
Provides-Extra: snowflake
Requires-Dist: snowflake-connector-python[pandas] ==3.6.0 ; extra == 'snowflake'
Provides-Extra: sqlserver
Requires-Dist: pyodbc ==4.0.39 ; extra == 'sqlserver'
